setup.cfg
setup.py
braveapi/__init__.py
braveapi/client.py
braveapi/controller.py
braveapi.egg-info/PKG-INFO
braveapi.egg-info/SOURCES.txt
braveapi.egg-info/dependency_links.txt
braveapi.egg-info/namespace_packages.txt
braveapi.egg-info/not-zip-safe
braveapi.egg-info/requires.txt
braveapi.egg-info/top_level.txt
tests/__init__.py