Metadata-Version: 1.0
Name: braveapi
Version: 0.3
Summary: Python API bindings for both utilizing and hosting the secure RPC mechanism.
Home-page: UNKNOWN
Author: Alice Bevan-McGregor
Author-email: alice@gothcandy.com
License: MIT
Platform: UNKNOWN
